cache3/__init__.py
cache3/disk.py
cache3/memory.py
cache3/util.py
cache3-0.4.3.dist-info/LICENSE
cache3-0.4.3.dist-info/METADATA
cache3-0.4.3.dist-info/WHEEL
cache3-0.4.3.dist-info/top_level.txt
cache3-0.4.3.dist-info/RECORD
