Metadata-Version: 2.1
Name: cache3
Version: 0.4.3
Summary: A safe and lightweight cache library, written in pure-Python.
Home-page: https://github.com/StKali/cache3
Author: attr: cache3.__author__
Author-email: clarkmonkey@163.com
License: MIT
Classifier: Development Status :: 4 - Beta
Classifier: Environment :: Other Environment
Classifier: Intended Audience :: Developers
Classifier: License :: OSI Approved :: MIT License
Classifier: Operating System :: OS Independent
Classifier: Programming Language :: Python :: 3.5
Classifier: Programming Language :: Python :: 3.7
Classifier: Programming Language :: Python :: 3.8
Classifier: Programming Language :: Python :: 3.9
Classifier: Programming Language :: Python :: 3.10
Classifier: Topic :: Software Development :: Libraries :: Python Modules
License-File: LICENSE
